fakeapi/__init__.py
fakeapi/__main__.py
fakeapi/_version.py
fakeapi/api.py
fakeapi/fakeserver.py
fakeapi/urlconfighelper.py
fakeapi/urlfunc.py
fakeapi-1.0.11.dist-info/LICENSE
fakeapi-1.0.11.dist-info/METADATA
fakeapi-1.0.11.dist-info/WHEEL
fakeapi-1.0.11.dist-info/top_level.txt
fakeapi-1.0.11.dist-info/RECORD
