Metadata-Version: 2.1
Name: fakeapi
Version: 1.0.11
Summary: Fake/Mock API Rest Calls requests
Home-page: https://github.com/joknarf/fakeapi
Author: joknarf
Author-email: joknarf@gmail.com
License: MIT
Keywords: requests API Rest api-client mock http
Classifier: Programming Language :: Python :: 3
Classifier: License :: OSI Approved :: MIT License
Classifier: Operating System :: POSIX
Classifier: Topic :: Utilities
License-File: LICENSE
Requires-Dist: incremental
